fictus/__init__.py
fictus/constants.py
fictus/fictusdisplay.py
fictus/fictusexception.py
fictus/fictusfilesystem.py
fictus/fictusnode.py
fictus/renderer.py
fictus-0.4.1.dist-info/LICENSE.md
fictus-0.4.1.dist-info/METADATA
fictus-0.4.1.dist-info/WHEEL
fictus-0.4.1.dist-info/top_level.txt
fictus-0.4.1.dist-info/RECORD
