Metadata-Version: 2.2
Name: fictus
Version: 0.4.1
Summary: Generate a fake file system to create documentation examples.
Author-email: Jason Brackman <brackman+fictus@gmail.com>
Project-URL: Homepage, https://github.com/jasonbrackman/arborator
Project-URL: Source, https://github.com/jasonbrackman/arborator
Keywords: documentation,fake,directory,filesystem
Classifier: Programming Language :: Python :: 3
Classifier: License :: OSI Approved :: MIT License
Classifier: Operating System :: OS Independent
Requires-Python: >=3.7
License-File: LICENSE.md
